ts2g/__init__.py
ts2g/calculate.py
ts2g/read.py
ts2g/save.py
ts2g-0.0.3.dist-info/LICENSE
ts2g-0.0.3.dist-info/METADATA
ts2g-0.0.3.dist-info/WHEEL
ts2g-0.0.3.dist-info/top_level.txt
ts2g-0.0.3.dist-info/RECORD
