Metadata-Version: 2.1
Name: ts2g
Version: 0.0.3
Summary: Converting time-series to graph using three different method which are natural visibility graph, horizontal visibility graph, and quantile graph
Home-page: https://github.com/k4my4r/ts2g
Author: Kamyar Zeinalipour
Author-email: k4my_r@yahoo.com
License: UNKNOWN
Project-URL: Bug Tracker, https://github.com/k4my4r/ts2g/issues
Platform: UNKNOWN
Classifier: Programming Language :: Python :: 3
Classifier: License :: OSI Approved :: MIT License
Classifier: Operating System :: OS Independent
Requires-Python: >=3.6
License-File: LICENSE
